[
  {
    "id": 186966,
    "slug": "rakietmania",
    "name": "Rakietmania",
    "link": "https://padellands.com/pistas-de-padel/rakietmania/",
    "avatarUrl": null,
    "courtsNumber": null,
    "cityFromDesc": null,
    "description": "",
    "sourceUrl": "https://padellands.com/pistas-de-padel/rakietmania/",
    "cityRaw": "Lublin",
    "address": "Lublin",
    "phone": null,
    "website": null,
    "latitude": null,
    "longitude": null,
    "regionSlug": "polonia",
    "regionName": "Poland"
  },
  {
    "id": 186967,
    "slug": "rakiety-pge-narodowy-outdoor",
    "name": "Rakiety PGE Narodowy outdoor",
    "link": "https://padellands.com/pistas-de-padel/rakiety-pge-narodowy-outdoor/",
    "avatarUrl": null,
    "courtsNumber": null,
    "cityFromDesc": null,
    "description": "",
    "sourceUrl": "https://padellands.com/pistas-de-padel/rakiety-pge-narodowy-outdoor/",
    "cityRaw": "Warszawa",
    "address": "Warszawa",
    "phone": null,
    "website": null,
    "latitude": null,
    "longitude": null,
    "regionSlug": "polonia",
    "regionName": "Poland"
  },
  {
    "id": 186968,
    "slug": "reyon-bytom",
    "name": "Reyon Bytom",
    "link": "https://padellands.com/pistas-de-padel/reyon-bytom/",
    "avatarUrl": null,
    "courtsNumber": null,
    "cityFromDesc": null,
    "description": "",
    "sourceUrl": "https://padellands.com/pistas-de-padel/reyon-bytom/",
    "cityRaw": "Bytom",
    "address": "Bytom",
    "phone": null,
    "website": null,
    "latitude": null,
    "longitude": null,
    "regionSlug": "polonia",
    "regionName": "Poland"
  },
  {
    "id": 186969,
    "slug": "net-padel-country-club",
    "name": "NET Padel Country Club",
    "link": "https://padellands.com/pistas-de-padel/net-padel-country-club/",
    "avatarUrl": null,
    "courtsNumber": null,
    "cityFromDesc": null,
    "description": "",
    "sourceUrl": "https://padellands.com/pistas-de-padel/net-padel-country-club/",
    "cityRaw": "Kielczow",
    "address": "Kielczow",
    "phone": null,
    "website": null,
    "latitude": null,
    "longitude": null,
    "regionSlug": "polonia",
    "regionName": "Poland"
  },
  {
    "id": 186970,
    "slug": "mypadel-zlotniki",
    "name": "MyPadel Złotniki",
    "link": "https://padellands.com/pistas-de-padel/mypadel-zlotniki/",
    "avatarUrl": null,
    "courtsNumber": null,
    "cityFromDesc": null,
    "description": "",
    "sourceUrl": "https://padellands.com/pistas-de-padel/mypadel-zlotniki/",
    "cityRaw": "Zlotniki",
    "address": "Zlotniki",
    "phone": null,
    "website": null,
    "latitude": null,
    "longitude": null,
    "regionSlug": "polonia",
    "regionName": "Poland"
  },
  {
    "id": 186957,
    "slug": "wejher-padel-club",
    "name": "Wejher Padel Club",
    "link": "https://padellands.com/pistas-de-padel/wejher-padel-club/",
    "avatarUrl": null,
    "courtsNumber": null,
    "cityFromDesc": null,
    "description": "",
    "sourceUrl": "https://padellands.com/pistas-de-padel/wejher-padel-club/",
    "cityRaw": "Wejherowo",
    "address": "Wejherowo",
    "phone": null,
    "website": null,
    "latitude": null,
    "longitude": null,
    "regionSlug": "polonia",
    "regionName": "Poland"
  },
  {
    "id": 186958,
    "slug": "garden-padel-krakow",
    "name": "Garden Padel Kraków",
    "link": "https://padellands.com/pistas-de-padel/garden-padel-krakow/",
    "avatarUrl": null,
    "courtsNumber": null,
    "cityFromDesc": null,
    "description": "",
    "sourceUrl": "https://padellands.com/pistas-de-padel/garden-padel-krakow/",
    "cityRaw": "Kraków",
    "address": "Kraków",
    "phone": null,
    "website": null,
    "latitude": null,
    "longitude": null,
    "regionSlug": "polonia",
    "regionName": "Poland"
  },
  {
    "id": 186959,
    "slug": "bajada-padel-club-krakow",
    "name": "Bajada padel Club Kraków",
    "link": "https://padellands.com/pistas-de-padel/bajada-padel-club-krakow/",
    "avatarUrl": null,
    "courtsNumber": null,
    "cityFromDesc": null,
    "description": "",
    "sourceUrl": "https://padellands.com/pistas-de-padel/bajada-padel-club-krakow/",
    "cityRaw": "Kraków",
    "address": "Kraków",
    "phone": null,
    "website": null,
    "latitude": null,
    "longitude": null,
    "regionSlug": "polonia",
    "regionName": "Poland"
  },
  {
    "id": 186960,
    "slug": "interpadel-poznan",
    "name": "Interpadel Poznań",
    "link": "https://padellands.com/pistas-de-padel/interpadel-poznan/",
    "avatarUrl": null,
    "courtsNumber": null,
    "cityFromDesc": null,
    "description": "",
    "sourceUrl": "https://padellands.com/pistas-de-padel/interpadel-poznan/",
    "cityRaw": "Poznań",
    "address": "Poznań",
    "phone": null,
    "website": null,
    "latitude": null,
    "longitude": null,
    "regionSlug": "polonia",
    "regionName": "Poland"
  },
  {
    "id": 186961,
    "slug": "fast-tennis-padel-club",
    "name": "Fast Tennis & Padel Club",
    "link": "https://padellands.com/pistas-de-padel/fast-tennis-padel-club/",
    "avatarUrl": null,
    "courtsNumber": null,
    "cityFromDesc": null,
    "description": "",
    "sourceUrl": "https://padellands.com/pistas-de-padel/fast-tennis-padel-club/",
    "cityRaw": "Bydgoszcz",
    "address": "Bydgoszcz",
    "phone": null,
    "website": null,
    "latitude": null,
    "longitude": null,
    "regionSlug": "polonia",
    "regionName": "Poland"
  },
  {
    "id": 186962,
    "slug": "pura-padel-bydgoszcz",
    "name": "Pura Padel Bydgoszcz",
    "link": "https://padellands.com/pistas-de-padel/pura-padel-bydgoszcz/",
    "avatarUrl": null,
    "courtsNumber": null,
    "cityFromDesc": null,
    "description": "",
    "sourceUrl": "https://padellands.com/pistas-de-padel/pura-padel-bydgoszcz/",
    "cityRaw": "Bydgoszcz",
    "address": "Bydgoszcz",
    "phone": null,
    "website": null,
    "latitude": null,
    "longitude": null,
    "regionSlug": "polonia",
    "regionName": "Poland"
  },
  {
    "id": 186963,
    "slug": "padel-park-bydgoszcz",
    "name": "Padel Park Bydgoszcz",
    "link": "https://padellands.com/pistas-de-padel/padel-park-bydgoszcz/",
    "avatarUrl": null,
    "courtsNumber": null,
    "cityFromDesc": null,
    "description": "",
    "sourceUrl": "https://padellands.com/pistas-de-padel/padel-park-bydgoszcz/",
    "cityRaw": "Bydgoszcz",
    "address": "Bydgoszcz",
    "phone": null,
    "website": null,
    "latitude": null,
    "longitude": null,
    "regionSlug": "polonia",
    "regionName": "Poland"
  },
  {
    "id": 186964,
    "slug": "padel-point-zemborzycka",
    "name": "Padel Point Zemborzycka",
    "link": "https://padellands.com/pistas-de-padel/padel-point-zemborzycka/",
    "avatarUrl": null,
    "courtsNumber": null,
    "cityFromDesc": null,
    "description": "",
    "sourceUrl": "https://padellands.com/pistas-de-padel/padel-point-zemborzycka/",
    "cityRaw": "Lublin",
    "address": "Lublin",
    "phone": null,
    "website": null,
    "latitude": null,
    "longitude": null,
    "regionSlug": "polonia",
    "regionName": "Poland"
  },
  {
    "id": 186965,
    "slug": "padel-point-lublin",
    "name": "Padel Point Lublin",
    "link": "https://padellands.com/pistas-de-padel/padel-point-lublin/",
    "avatarUrl": null,
    "courtsNumber": null,
    "cityFromDesc": null,
    "description": "",
    "sourceUrl": "https://padellands.com/pistas-de-padel/padel-point-lublin/",
    "cityRaw": "Lublin",
    "address": "Lublin",
    "phone": null,
    "website": null,
    "latitude": null,
    "longitude": null,
    "regionSlug": "polonia",
    "regionName": "Poland"
  },
  {
    "id": 186952,
    "slug": "korty-nowosolna",
    "name": "Korty Nowosolna",
    "link": "https://padellands.com/pistas-de-padel/korty-nowosolna/",
    "avatarUrl": null,
    "courtsNumber": null,
    "cityFromDesc": null,
    "description": "",
    "sourceUrl": "https://padellands.com/pistas-de-padel/korty-nowosolna/",
    "cityRaw": "Łódź",
    "address": "Łódź",
    "phone": null,
    "website": null,
    "latitude": null,
    "longitude": null,
    "regionSlug": "polonia",
    "regionName": "Poland"
  },
  {
    "id": 186953,
    "slug": "stacja-padel",
    "name": "Stacja Padel",
    "link": "https://padellands.com/pistas-de-padel/stacja-padel/",
    "avatarUrl": null,
    "courtsNumber": null,
    "cityFromDesc": null,
    "description": "",
    "sourceUrl": "https://padellands.com/pistas-de-padel/stacja-padel/",
    "cityRaw": "Łódź",
    "address": "Łódź",
    "phone": null,
    "website": null,
    "latitude": null,
    "longitude": null,
    "regionSlug": "polonia",
    "regionName": "Poland"
  },
  {
    "id": 186954,
    "slug": "baza-sport-suchy-dwor",
    "name": "Baza Sport Suchy Dwór",
    "link": "https://padellands.com/pistas-de-padel/baza-sport-suchy-dwor/",
    "avatarUrl": null,
    "courtsNumber": null,
    "cityFromDesc": null,
    "description": "",
    "sourceUrl": "https://padellands.com/pistas-de-padel/baza-sport-suchy-dwor/",
    "cityRaw": "Pogorze",
    "address": "Pogorze",
    "phone": null,
    "website": null,
    "latitude": null,
    "longitude": null,
    "regionSlug": "polonia",
    "regionName": "Poland"
  },
  {
    "id": 186955,
    "slug": "padel-park-gdansk",
    "name": "Padel Park Gdansk",
    "link": "https://padellands.com/pistas-de-padel/padel-park-gdansk/",
    "avatarUrl": null,
    "courtsNumber": null,
    "cityFromDesc": null,
    "description": "",
    "sourceUrl": "https://padellands.com/pistas-de-padel/padel-park-gdansk/",
    "cityRaw": "Pruszcz Gdanski",
    "address": "Pruszcz Gdanski",
    "phone": null,
    "website": null,
    "latitude": null,
    "longitude": null,
    "regionSlug": "polonia",
    "regionName": "Poland"
  },
  {
    "id": 186956,
    "slug": "leo-racket-club-straszyn",
    "name": "Leo Racket Club – Straszyn",
    "link": "https://padellands.com/pistas-de-padel/leo-racket-club-straszyn/",
    "avatarUrl": null,
    "courtsNumber": null,
    "cityFromDesc": null,
    "description": "",
    "sourceUrl": "https://padellands.com/pistas-de-padel/leo-racket-club-straszyn/",
    "cityRaw": "Straszyn",
    "address": "Straszyn",
    "phone": null,
    "website": null,
    "latitude": null,
    "longitude": null,
    "regionSlug": "polonia",
    "regionName": "Poland"
  },
  {
    "id": 185452,
    "slug": "leo-racket-club",
    "name": "Leo Racket Club",
    "link": "https://padellands.com/pistas-de-padel/leo-racket-club/",
    "avatarUrl": "https://padellands.com/wp-content/uploads/2026/06/Leo-Racket-Club.jpg",
    "courtsNumber": 2,
    "cityFromDesc": "Trąbki Wielkie",
    "description": "Leo Racket Club os ofrece jugar en 2 pistas de padel en Trąbki Wielkie, Polonia. 2 padel courts in Trąbki Wielkie, Poland.",
    "sourceUrl": "https://padellands.com/pistas-de-padel/leo-racket-club/",
    "cityRaw": "Trabki Wielkie",
    "address": "Trabki Wielkie",
    "phone": null,
    "website": null,
    "latitude": null,
    "longitude": null,
    "regionSlug": "polonia",
    "regionName": "Poland"
  },
  {
    "id": 185453,
    "slug": "centrum-tenisowe-arena",
    "name": "Centrum Tenisowe Arena",
    "link": "https://padellands.com/pistas-de-padel/centrum-tenisowe-arena/",
    "avatarUrl": null,
    "courtsNumber": 4,
    "cityFromDesc": "Poznań",
    "description": "Centrum Tenisowe Arena es un club de raqueta con 4 pistas de padel en Poznań, Polonia. 4 padel courts in Poznań, Poland.",
    "sourceUrl": "https://padellands.com/pistas-de-padel/centrum-tenisowe-arena/",
    "cityRaw": "Poznań",
    "address": "Poznań",
    "phone": null,
    "website": null,
    "latitude": null,
    "longitude": null,
    "regionSlug": "polonia",
    "regionName": "Poland"
  },
  {
    "id": 185445,
    "slug": "kortmax-tennis-padel-club",
    "name": "Kortmax Tennis & Padel Club",
    "link": "https://padellands.com/pistas-de-padel/kortmax-tennis-padel-club/",
    "avatarUrl": "https://padellands.com/wp-content/uploads/2026/06/Kortmax-Tennis-Padel-Club-.jpg",
    "courtsNumber": 2,
    "cityFromDesc": "Błonie",
    "description": "Kortmax Tennis & Padel Club os ofrece 2 pistas de padel en Błonie, Polonia. 2 padel courts in Błonie, Poland.",
    "sourceUrl": "https://padellands.com/pistas-de-padel/kortmax-tennis-padel-club/",
    "cityRaw": "Blonie",
    "address": "Blonie",
    "phone": null,
    "website": null,
    "latitude": null,
    "longitude": null,
    "regionSlug": "polonia",
    "regionName": "Poland"
  },
  {
    "id": 185446,
    "slug": "toro-padel-warszawa",
    "name": "Toro Padel Warszawa",
    "link": "https://padellands.com/pistas-de-padel/toro-padel-warszawa/",
    "avatarUrl": "https://padellands.com/wp-content/uploads/2026/06/Toro-Padel-Warszawa-.jpg",
    "courtsNumber": 6,
    "cityFromDesc": null,
    "description": "Toro Padel Warszawa os propone jugar en sus 6 pistas de padel en Varsovia, Polonia. 6 padel courts in Varsovia, Poland.",
    "sourceUrl": "https://padellands.com/pistas-de-padel/toro-padel-warszawa/",
    "cityRaw": "Varsovia",
    "address": "Varsovia",
    "phone": null,
    "website": null,
    "latitude": null,
    "longitude": null,
    "regionSlug": "polonia",
    "regionName": "Poland"
  },
  {
    "id": 185447,
    "slug": "loba-padel",
    "name": "Loba Padel",
    "link": "https://padellands.com/pistas-de-padel/loba-padel/",
    "avatarUrl": "https://padellands.com/wp-content/uploads/2026/06/Loba-Padel.jpg",
    "courtsNumber": 8,
    "cityFromDesc": "Varsovia",
    "description": "Loba Padel es un club que ofrece 8 pistas de padel en Varsovia, Polonia. 8 padel courts in Varsovia, Poland.",
    "sourceUrl": "https://padellands.com/pistas-de-padel/loba-padel/",
    "cityRaw": "Varsovia",
    "address": "Varsovia",
    "phone": null,
    "website": null,
    "latitude": null,
    "longitude": null,
    "regionSlug": "polonia",
    "regionName": "Poland"
  },
  {
    "id": 185448,
    "slug": "sporteum",
    "name": "Sporteum",
    "link": "https://padellands.com/pistas-de-padel/sporteum/",
    "avatarUrl": "https://padellands.com/wp-content/uploads/2026/06/Sporteum.jpg",
    "courtsNumber": 2,
    "cityFromDesc": "Varsovia",
    "description": "Sporteum es un club deportivo con 2 pistas de padel en Varsovia, Polonia. 2 padel courts in Varsovia, Poland.",
    "sourceUrl": "https://padellands.com/pistas-de-padel/sporteum/",
    "cityRaw": "Varsovia",
    "address": "Varsovia",
    "phone": null,
    "website": null,
    "latitude": null,
    "longitude": null,
    "regionSlug": "polonia",
    "regionName": "Poland"
  },
  {
    "id": 185449,
    "slug": "teniswil",
    "name": "TenisWil",
    "link": "https://padellands.com/pistas-de-padel/teniswil/",
    "avatarUrl": "https://padellands.com/wp-content/uploads/2026/06/TenisWil-.jpg",
    "courtsNumber": 3,
    "cityFromDesc": "Varsovia",
    "description": "TenisWil es un club de tenis con 3 pistas de padel situadas en Varsovia, Polonia. 3 padel courts in Varsovia, Poland.",
    "sourceUrl": "https://padellands.com/pistas-de-padel/teniswil/",
    "cityRaw": "Varsovia",
    "address": "Varsovia",
    "phone": null,
    "website": null,
    "latitude": null,
    "longitude": null,
    "regionSlug": "polonia",
    "regionName": "Poland"
  },
  {
    "id": 185450,
    "slug": "klub-miedzeszyn",
    "name": "Klub Miedzeszyn",
    "link": "https://padellands.com/pistas-de-padel/klub-miedzeszyn/",
    "avatarUrl": "https://padellands.com/wp-content/uploads/2026/06/Klub-Miedzeszyn.png",
    "courtsNumber": 2,
    "cityFromDesc": "Klub Miedzeszyn",
    "description": "Klub Miedzeszyn pone a vuestra disposición 2 pistas de padel en Klub Miedzeszyn, Polonia. 2 padel courts in Klub Miedzeszyn, Poland.",
    "sourceUrl": "https://padellands.com/pistas-de-padel/klub-miedzeszyn/",
    "cityRaw": "Klub Miedzeszyn",
    "address": "Klub Miedzeszyn",
    "phone": null,
    "website": null,
    "latitude": null,
    "longitude": null,
    "regionSlug": "polonia",
    "regionName": "Poland"
  },
  {
    "id": 185451,
    "slug": "sanpadel-mysiadlo",
    "name": "SanPadel Mysiadło",
    "link": "https://padellands.com/pistas-de-padel/sanpadel-mysiadlo/",
    "avatarUrl": "https://padellands.com/wp-content/uploads/2026/06/SanPadel-Mysiadlo-.jpg",
    "courtsNumber": 12,
    "cityFromDesc": "Mysiadło",
    "description": "SanPadel Mysiadło dispone de 12 pistas de padel en Mysiadło, Polonia. 12 padel courts in Mysiadło, Poland.",
    "sourceUrl": "https://padellands.com/pistas-de-padel/sanpadel-mysiadlo/",
    "cityRaw": "Mysiadlo",
    "address": "Mysiadlo",
    "phone": null,
    "website": null,
    "latitude": null,
    "longitude": null,
    "regionSlug": "polonia",
    "regionName": "Poland"
  },
  {
    "id": 174679,
    "slug": "baltic-padel-club",
    "name": "Baltic Padel Club",
    "link": "https://padellands.com/pistas-de-padel/baltic-padel-club/",
    "avatarUrl": "https://padellands.com/wp-content/uploads/2025/10/Baltic-Padel-Club-.jpg",
    "courtsNumber": 7,
    "cityFromDesc": null,
    "description": "Baltic Padel Club os ofrece jugar en sus 7 pistas de padel ubicadas en Gdynia, Polonia. 7 padel courts in Gdynia, Poland.",
    "sourceUrl": "https://padellands.com/pistas-de-padel/baltic-padel-club/",
    "cityRaw": "Gdynia",
    "address": "Gdynia",
    "phone": null,
    "website": null,
    "latitude": null,
    "longitude": null,
    "regionSlug": "polonia",
    "regionName": "Poland"
  },
  {
    "id": 174670,
    "slug": "mana-padel",
    "name": "Mana Padel",
    "link": "https://padellands.com/pistas-de-padel/mana-padel/",
    "avatarUrl": "https://padellands.com/wp-content/uploads/2025/10/Mana-Padel.jpg",
    "courtsNumber": 8,
    "cityFromDesc": "Vaesovia",
    "description": "Mana Padel cuenta con 8 pistas de padel localizadas en Vaesovia, Polonia. 8 padel courts in Warszawa, Poland.",
    "sourceUrl": "https://padellands.com/pistas-de-padel/mana-padel/",
    "cityRaw": "Warszawa",
    "address": "Warszawa",
    "phone": null,
    "website": null,
    "latitude": null,
    "longitude": null,
    "regionSlug": "polonia",
    "regionName": "Poland"
  },
  {
    "id": 168631,
    "slug": "padel-center-academy-katowice",
    "name": "Padel Center Academy Katowice",
    "link": "https://padellands.com/pistas-de-padel/padel-center-academy-katowice/",
    "avatarUrl": "https://padellands.com/wp-content/uploads/2025/07/Padel-Center-Academy-Katowice-.jpg",
    "courtsNumber": 9,
    "cityFromDesc": "Katowice",
    "description": "Padel Center Academy Katowice. Club con 9 pistas de padel en Katowice, Polonia. 9 padel courts in Katowice, Poland.",
    "sourceUrl": "https://padellands.com/pistas-de-padel/padel-center-academy-katowice/",
    "cityRaw": "Katowice",
    "address": "Katowice",
    "phone": null,
    "website": null,
    "latitude": null,
    "longitude": null,
    "regionSlug": "polonia",
    "regionName": "Poland"
  },
  {
    "id": 166132,
    "slug": "warsaw-padel-club",
    "name": "Warsaw Padel Club",
    "link": "https://padellands.com/pistas-de-padel/warsaw-padel-club/",
    "avatarUrl": "https://padellands.com/wp-content/uploads/2025/05/Warsaw-Padel-Club.jpg",
    "courtsNumber": 11,
    "cityFromDesc": "Varsovia",
    "description": "Warsaw Padel Club cuenta con 11 pistas de padel en Varsovia, Polonia. 11 padel courts in Warszawa, Polonia.",
    "sourceUrl": "https://padellands.com/pistas-de-padel/warsaw-padel-club/",
    "cityRaw": "Varsovia",
    "address": "Varsovia",
    "phone": null,
    "website": null,
    "latitude": null,
    "longitude": null,
    "regionSlug": "polonia",
    "regionName": "Poland"
  },
  {
    "id": 165283,
    "slug": "padel-club-szczecin",
    "name": "Padel Club Szczecin",
    "link": "https://padellands.com/pistas-de-padel/padel-club-szczecin/",
    "avatarUrl": "https://padellands.com/wp-content/uploads/2025/04/Padel-Club-Szczecin-.jpg",
    "courtsNumber": 5,
    "cityFromDesc": "Szczecin",
    "description": "Padel Club Szczecin dispone de 5 pistas de padel ubicadas en Szczecin, Polonia. 5 padel courts in Szczecin, Polonia.",
    "sourceUrl": "https://padellands.com/pistas-de-padel/padel-club-szczecin/",
    "cityRaw": "Szczecin",
    "address": "Szczecin",
    "phone": null,
    "website": null,
    "latitude": null,
    "longitude": null,
    "regionSlug": "polonia",
    "regionName": "Poland"
  },
  {
    "id": 163349,
    "slug": "plek-padel-poznan",
    "name": "PLEK Padel Poznań",
    "link": "https://padellands.com/pistas-de-padel/plek-padel-poznan/",
    "avatarUrl": "https://padellands.com/wp-content/uploads/2025/02/PLEK-Padel-Poznan-.jpg",
    "courtsNumber": 5,
    "cityFromDesc": "Poznan",
    "description": "PLEK Padel Poznań. Centro deportivo con 5 pistas de padel en Poznan, Polonia. 5 padel courts in Poznan, Polonia.",
    "sourceUrl": "https://padellands.com/pistas-de-padel/plek-padel-poznan/",
    "cityRaw": "Poznań",
    "address": "Poznań",
    "phone": null,
    "website": null,
    "latitude": null,
    "longitude": null,
    "regionSlug": "polonia",
    "regionName": "Poland"
  },
  {
    "id": 156013,
    "slug": "aerosquash",
    "name": "Aerosquash",
    "link": "https://padellands.com/pistas-de-padel/aerosquash/",
    "avatarUrl": "https://padellands.com/wp-content/uploads/2024/09/Aerosquash-.jpg",
    "courtsNumber": null,
    "cityFromDesc": "Varsovia",
    "description": "Aerosquash es un club de squash que dispone de una pista de padel en Varsovia, Polonia. Padel court in Warsaw, Poland.",
    "sourceUrl": "https://padellands.com/pistas-de-padel/aerosquash/",
    "cityRaw": "Warszawa",
    "address": "Warszawa",
    "phone": null,
    "website": null,
    "latitude": null,
    "longitude": null,
    "regionSlug": "polonia",
    "regionName": "Poland"
  },
  {
    "id": 156009,
    "slug": "tenes-klub-sportowy",
    "name": "TENES Klub Sportowy",
    "link": "https://padellands.com/pistas-de-padel/tenes-klub-sportowy/",
    "avatarUrl": "https://padellands.com/wp-content/uploads/2024/09/TENES-Klub-Sportowy.jpg",
    "courtsNumber": 3,
    "cityFromDesc": "Jawczyce",
    "description": "TENES Klub Sportowy es un club deportivo con 3 pistas de padel en Jawczyce, Polonia. 3 padel courts in Jawczyce, Poland.",
    "sourceUrl": "https://padellands.com/pistas-de-padel/tenes-klub-sportowy/",
    "cityRaw": "Jawczyce",
    "address": "Jawczyce",
    "phone": null,
    "website": null,
    "latitude": null,
    "longitude": null,
    "regionSlug": "polonia",
    "regionName": "Poland"
  },
  {
    "id": 156005,
    "slug": "klub-sportowy-perla",
    "name": "Klub Sportowy Perla",
    "link": "https://padellands.com/pistas-de-padel/klub-sportowy-perla/",
    "avatarUrl": "https://padellands.com/wp-content/uploads/2024/09/Klub-Sportowy-Perla-.jpg",
    "courtsNumber": null,
    "cityFromDesc": "Słupsk",
    "description": "Klub Sportowy Perla. Club deportivo que dispone de una pista de padel en Słupsk, Polonia. Padel court in Słupsk, Poland.",
    "sourceUrl": "https://padellands.com/pistas-de-padel/klub-sportowy-perla/",
    "cityRaw": "Slupsk",
    "address": "Slupsk",
    "phone": null,
    "website": null,
    "latitude": null,
    "longitude": null,
    "regionSlug": "polonia",
    "regionName": "Poland"
  },
  {
    "id": 156001,
    "slug": "ahoj-padel",
    "name": "Ahoj Padel",
    "link": "https://padellands.com/pistas-de-padel/ahoj-padel/",
    "avatarUrl": "https://padellands.com/wp-content/uploads/2024/09/Ahoj-Padel-.jpg",
    "courtsNumber": 4,
    "cityFromDesc": "Staniątki",
    "description": "Ahoj Padel es un club que cuenta con 4 pistas de padel ubicadas en Staniątki, Polonia. 4 padel courts in Staniątki, Poland.",
    "sourceUrl": "https://padellands.com/pistas-de-padel/ahoj-padel/",
    "cityRaw": "Staniatki",
    "address": "Staniatki",
    "phone": null,
    "website": null,
    "latitude": null,
    "longitude": null,
    "regionSlug": "polonia",
    "regionName": "Poland"
  },
  {
    "id": 155997,
    "slug": "passion-padel-poznan",
    "name": "Passion Padel Poznań",
    "link": "https://padellands.com/pistas-de-padel/passion-padel-poznan/",
    "avatarUrl": "https://padellands.com/wp-content/uploads/2024/09/Passion-Padel-Poznan-.jpg",
    "courtsNumber": 2,
    "cityFromDesc": "Poznań",
    "description": "Passion Padel Poznań ofrece unas instalaciones con 2 pistas de padel en Poznań, Polonia. 2 padel courts in Poznań, Poland.",
    "sourceUrl": "https://padellands.com/pistas-de-padel/passion-padel-poznan/",
    "cityRaw": "Poznań",
    "address": "Poznań",
    "phone": null,
    "website": null,
    "latitude": null,
    "longitude": null,
    "regionSlug": "polonia",
    "regionName": "Poland"
  },
  {
    "id": 155400,
    "slug": "akademia-padla",
    "name": "Akademia Padla",
    "link": "https://padellands.com/pistas-de-padel/akademia-padla/",
    "avatarUrl": "https://padellands.com/wp-content/uploads/2024/08/Akademia-Padla-.jpg",
    "courtsNumber": 4,
    "cityFromDesc": "Poznań",
    "description": "Akademia Padla es un centro que dispone de 4 pistas de padel en Poznań, Polonia. 4 padel courts in Poznań, Polonia.",
    "sourceUrl": "https://padellands.com/pistas-de-padel/akademia-padla/",
    "cityRaw": "Poznań",
    "address": "Poznań",
    "phone": null,
    "website": null,
    "latitude": null,
    "longitude": null,
    "regionSlug": "polonia",
    "regionName": "Poland"
  },
  {
    "id": 155396,
    "slug": "sport-beauty-fabianowo",
    "name": "Sport & Beauty Fabianowo",
    "link": "https://padellands.com/pistas-de-padel/sport-beauty-fabianowo/",
    "avatarUrl": "https://padellands.com/wp-content/uploads/2024/08/Sport-Beauty-Fabianowo-.jpg",
    "courtsNumber": null,
    "cityFromDesc": "Poznań",
    "description": "Sport & Beauty Fabianowo. Tres pistas de padel localizadas en Poznań, Polonia. 3 padel courts in Poznań, Polonia.",
    "sourceUrl": "https://padellands.com/pistas-de-padel/sport-beauty-fabianowo/",
    "cityRaw": "Poznań",
    "address": "Poznań",
    "phone": null,
    "website": null,
    "latitude": null,
    "longitude": null,
    "regionSlug": "polonia",
    "regionName": "Poland"
  },
  {
    "id": 155392,
    "slug": "rockets-center",
    "name": "Rockets Center",
    "link": "https://padellands.com/pistas-de-padel/rockets-center/",
    "avatarUrl": "https://padellands.com/wp-content/uploads/2024/08/Rockets-Center-.png",
    "courtsNumber": 2,
    "cityFromDesc": "Tarnowskie Góry",
    "description": "Rockets Center es un un club con 2 pistas de padel situado en Tarnowskie Góry, Polonia. 2 padel courts in Tarnowskie Góry, Polonia.",
    "sourceUrl": "https://padellands.com/pistas-de-padel/rockets-center/",
    "cityRaw": "Tarnowskie Gory",
    "address": "Tarnowskie Gory",
    "phone": null,
    "website": null,
    "latitude": null,
    "longitude": null,
    "regionSlug": "polonia",
    "regionName": "Poland"
  },
  {
    "id": 155388,
    "slug": "royal-tennis-club",
    "name": "Royal Tennis Club",
    "link": "https://padellands.com/pistas-de-padel/royal-tennis-club/",
    "avatarUrl": "https://padellands.com/wp-content/uploads/2024/08/Royal-Tennis-Club-.png",
    "courtsNumber": null,
    "cityFromDesc": "Kozy",
    "description": "Una pista de padel disponible en Royal Tennis Club, que se encuentra en Kozy, Polonia. Padel court in Kozy, Polonia.",
    "sourceUrl": "https://padellands.com/pistas-de-padel/royal-tennis-club/",
    "cityRaw": "Kozy",
    "address": "Kozy",
    "phone": null,
    "website": null,
    "latitude": null,
    "longitude": null,
    "regionSlug": "polonia",
    "regionName": "Poland"
  },
  {
    "id": 155384,
    "slug": "sport-park-slask",
    "name": "Sport Park Śląsk",
    "link": "https://padellands.com/pistas-de-padel/sport-park-slask/",
    "avatarUrl": "https://padellands.com/wp-content/uploads/2024/08/Sport-Park-Slask-.jpg",
    "courtsNumber": 5,
    "cityFromDesc": "Chorzów",
    "description": "Sport Park Śląsk. Centro deportivo que dispone de 5 pistas de padel en Chorzów, Polonia. 5 padel courts in Chorzów, Polonia.",
    "sourceUrl": "https://padellands.com/pistas-de-padel/sport-park-slask/",
    "cityRaw": "Chorzow",
    "address": "Chorzow",
    "phone": null,
    "website": null,
    "latitude": null,
    "longitude": null,
    "regionSlug": "polonia",
    "regionName": "Poland"
  },
  {
    "id": 155380,
    "slug": "centrum-sportow-rakietowych-platinum",
    "name": "Centrum Sportów Rakietowych Platinum",
    "link": "https://padellands.com/pistas-de-padel/centrum-sportow-rakietowych-platinum/",
    "avatarUrl": "https://padellands.com/wp-content/uploads/2024/08/Centrum-Sportow-Rakietowych-Platinum-.jpg",
    "courtsNumber": 2,
    "cityFromDesc": "Rybnik",
    "description": "Centrum Sportów Rakietowych Platinum cuenta con 2 pistas de padel en Rybnik, Polonia. 2 padel courts in Rybnik, Polonia.",
    "sourceUrl": "https://padellands.com/pistas-de-padel/centrum-sportow-rakietowych-platinum/",
    "cityRaw": "Rybnik",
    "address": "Rybnik",
    "phone": null,
    "website": null,
    "latitude": null,
    "longitude": null,
    "regionSlug": "polonia",
    "regionName": "Poland"
  },
  {
    "id": 154813,
    "slug": "padel4all-bulwary-wislane",
    "name": "Padel4All – Bulwary Wiślane",
    "link": "https://padellands.com/pistas-de-padel/padel4all-bulwary-wislane/",
    "avatarUrl": "https://padellands.com/wp-content/uploads/2024/08/Padel4All-Bulwary-Wislane.jpg",
    "courtsNumber": null,
    "cityFromDesc": null,
    "description": "Padel4All - Bulwary Wiślane dispone de una pista de padel en Padel4All - Bulwary Wiślane, Polonia. Padel court in Padel4All - Bulwary Wiślane.",
    "sourceUrl": "https://padellands.com/pistas-de-padel/padel4all-bulwary-wislane/",
    "cityRaw": "Warszawa",
    "address": "Warszawa",
    "phone": null,
    "website": null,
    "latitude": null,
    "longitude": null,
    "regionSlug": "polonia",
    "regionName": "Poland"
  },
  {
    "id": 153071,
    "slug": "ultra-padel-gliwice",
    "name": "Ultra Padel Gliwice",
    "link": "https://padellands.com/pistas-de-padel/ultra-padel-gliwice/",
    "avatarUrl": "https://padellands.com/wp-content/uploads/2024/06/ULTRA-PADEL-Gliwice-.jpg",
    "courtsNumber": 4,
    "cityFromDesc": "Gliwice",
    "description": "Ultra Padel Gliwice pone a disposición de sus visitantes 4 pistas de padel en Gliwice, Polonia. 4 padel courts in Gliwice, Polonia.",
    "sourceUrl": "https://padellands.com/pistas-de-padel/ultra-padel-gliwice/",
    "cityRaw": "Gliwice",
    "address": "Gliwice",
    "phone": null,
    "website": null,
    "latitude": null,
    "longitude": null,
    "regionSlug": "polonia",
    "regionName": "Poland"
  },
  {
    "id": 144338,
    "slug": "fabryka-energii",
    "name": "Fabryka Energii",
    "link": "https://padellands.com/pistas-de-padel/fabryka-energii/",
    "avatarUrl": "https://padellands.com/wp-content/uploads/2024/02/Fabryka-Energii-.jpg",
    "courtsNumber": null,
    "cityFromDesc": null,
    "description": "Fabryka Energii. Una pista de padel en sus instalaciones de Szczecin, Polonia. One padel court in Szczecin, Poland.",
    "sourceUrl": "https://padellands.com/pistas-de-padel/fabryka-energii/",
    "cityRaw": "Szczecin",
    "address": "Szczecin",
    "phone": null,
    "website": null,
    "latitude": null,
    "longitude": null,
    "regionSlug": "polonia",
    "regionName": "Poland"
  },
  {
    "id": 138534,
    "slug": "padelteam-tichy",
    "name": "PadelTeam Tichy",
    "link": "https://padellands.com/pistas-de-padel/padelteam-tichy/",
    "avatarUrl": null,
    "courtsNumber": 4,
    "cityFromDesc": "Żory",
    "description": "PadelTeam Tichy. Centros PadelTeam. 4 pistas de padel ubicadas en Żory, Polonia. 4 padel courts in Żory, Poland.",
    "sourceUrl": "https://padellands.com/pistas-de-padel/padelteam-tichy/",
    "cityRaw": "Zory",
    "address": "Zory",
    "phone": null,
    "website": null,
    "latitude": null,
    "longitude": null,
    "regionSlug": "polonia",
    "regionName": "Poland"
  },
  {
    "id": 128386,
    "slug": "showteam",
    "name": "SHOWteam",
    "link": "https://padellands.com/pistas-de-padel/showteam/",
    "avatarUrl": null,
    "courtsNumber": null,
    "cityFromDesc": null,
    "description": "",
    "sourceUrl": "https://padellands.com/pistas-de-padel/showteam/",
    "cityRaw": "Poreba",
    "address": "Poreba",
    "phone": null,
    "website": null,
    "latitude": null,
    "longitude": null,
    "regionSlug": "polonia",
    "regionName": "Poland"
  },
  {
    "id": 128387,
    "slug": "mosir-zory",
    "name": "MOSiR Żory",
    "link": "https://padellands.com/pistas-de-padel/mosir-zory/",
    "avatarUrl": "https://padellands.com/wp-content/uploads/2023/09/2ff8cc3d638ff7f09c88407617d06be6.png",
    "courtsNumber": null,
    "cityFromDesc": null,
    "description": "",
    "sourceUrl": "https://padellands.com/pistas-de-padel/mosir-zory/",
    "cityRaw": "Zory",
    "address": "Zory",
    "phone": null,
    "website": null,
    "latitude": null,
    "longitude": null,
    "regionSlug": "polonia",
    "regionName": "Poland"
  },
  {
    "id": 128388,
    "slug": "otwocka-akademia-tenisa-prestigecourt",
    "name": "Otwocka Akademia Tenisa “PrestigeCourt”",
    "link": "https://padellands.com/pistas-de-padel/otwocka-akademia-tenisa-prestigecourt/",
    "avatarUrl": "https://padellands.com/wp-content/uploads/2023/09/5a8e3ea760b81e91b3ccd3a0669c57ff.png",
    "courtsNumber": null,
    "cityFromDesc": null,
    "description": "",
    "sourceUrl": "https://padellands.com/pistas-de-padel/otwocka-akademia-tenisa-prestigecourt/",
    "cityRaw": "Otwock",
    "address": "Otwock",
    "phone": null,
    "website": null,
    "latitude": null,
    "longitude": null,
    "regionSlug": "polonia",
    "regionName": "Poland"
  },
  {
    "id": 128389,
    "slug": "padlovnia",
    "name": "Padlovnia",
    "link": "https://padellands.com/pistas-de-padel/padlovnia/",
    "avatarUrl": "https://padellands.com/wp-content/uploads/2023/09/054236928a3e96efbc7855b044ea66c9.jpeg",
    "courtsNumber": null,
    "cityFromDesc": null,
    "description": "",
    "sourceUrl": "https://padellands.com/pistas-de-padel/padlovnia/",
    "cityRaw": "Warszawa",
    "address": "Warszawa",
    "phone": null,
    "website": null,
    "latitude": null,
    "longitude": null,
    "regionSlug": "polonia",
    "regionName": "Poland"
  },
  {
    "id": 128380,
    "slug": "gdynia-padel-club",
    "name": "Gdynia PADEL CLUB",
    "link": "https://padellands.com/pistas-de-padel/gdynia-padel-club/",
    "avatarUrl": "https://padellands.com/wp-content/uploads/2023/09/a28f912d65c4f4bef19101ccb8918908.jpeg",
    "courtsNumber": null,
    "cityFromDesc": null,
    "description": "",
    "sourceUrl": "https://padellands.com/pistas-de-padel/gdynia-padel-club/",
    "cityRaw": "Gdynia",
    "address": "Gdynia",
    "phone": null,
    "website": null,
    "latitude": null,
    "longitude": null,
    "regionSlug": "polonia",
    "regionName": "Poland"
  },
  {
    "id": 128381,
    "slug": "padbox-centrum-sportowe",
    "name": "Padbox Centrum Sportowe",
    "link": "https://padellands.com/pistas-de-padel/padbox-centrum-sportowe/",
    "avatarUrl": "https://padellands.com/wp-content/uploads/2023/09/218feb46c64bdd5f0b608a104409a0f3.jpeg",
    "courtsNumber": null,
    "cityFromDesc": null,
    "description": "",
    "sourceUrl": "https://padellands.com/pistas-de-padel/padbox-centrum-sportowe/",
    "cityRaw": "Gdańsk",
    "address": "Gdańsk",
    "phone": null,
    "website": null,
    "latitude": null,
    "longitude": null,
    "regionSlug": "polonia",
    "regionName": "Poland"
  },
  {
    "id": 128382,
    "slug": "posir",
    "name": "Posir",
    "link": "https://padellands.com/pistas-de-padel/posir/",
    "avatarUrl": "https://padellands.com/wp-content/uploads/2023/09/e7196ac06a703a9e6a2d0e58e58102e0.png",
    "courtsNumber": null,
    "cityFromDesc": null,
    "description": "",
    "sourceUrl": "https://padellands.com/pistas-de-padel/posir/",
    "cityRaw": "Poznań",
    "address": "Poznań",
    "phone": null,
    "website": null,
    "latitude": null,
    "longitude": null,
    "regionSlug": "polonia",
    "regionName": "Poland"
  },
  {
    "id": 128383,
    "slug": "akademia-tenisa-matchball",
    "name": "Akademia Tenisa Matchball",
    "link": "https://padellands.com/pistas-de-padel/akademia-tenisa-matchball/",
    "avatarUrl": "https://padellands.com/wp-content/uploads/2023/09/523c64bb6719bd206dd87408c7eedde4.jpeg",
    "courtsNumber": null,
    "cityFromDesc": null,
    "description": "",
    "sourceUrl": "https://padellands.com/pistas-de-padel/akademia-tenisa-matchball/",
    "cityRaw": "Bydgoszcz",
    "address": "Bydgoszcz",
    "phone": null,
    "website": null,
    "latitude": null,
    "longitude": null,
    "regionSlug": "polonia",
    "regionName": "Poland"
  },
  {
    "id": 128384,
    "slug": "squash-tarnow",
    "name": "Squash Tarnów",
    "link": "https://padellands.com/pistas-de-padel/squash-tarnow/",
    "avatarUrl": "https://padellands.com/wp-content/uploads/2023/09/8625525e0fd13007257d5b9b0d1bf5c5.jpeg",
    "courtsNumber": null,
    "cityFromDesc": null,
    "description": "",
    "sourceUrl": "https://padellands.com/pistas-de-padel/squash-tarnow/",
    "cityRaw": "Tarnow",
    "address": "Tarnow",
    "phone": null,
    "website": null,
    "latitude": null,
    "longitude": null,
    "regionSlug": "polonia",
    "regionName": "Poland"
  },
  {
    "id": 128369,
    "slug": "garden-club-sportshealth",
    "name": "Garden Club Sports&Health",
    "link": "https://padellands.com/pistas-de-padel/garden-club-sportshealth/",
    "avatarUrl": "https://padellands.com/wp-content/uploads/2023/09/750a04f4875c6e39c528aa9b4e62b5d1.jpg",
    "courtsNumber": null,
    "cityFromDesc": null,
    "description": "",
    "sourceUrl": "https://padellands.com/pistas-de-padel/garden-club-sportshealth/",
    "cityRaw": "Konstancin Jeziorna",
    "address": "Konstancin Jeziorna",
    "phone": null,
    "website": null,
    "latitude": null,
    "longitude": null,
    "regionSlug": "polonia",
    "regionName": "Poland"
  },
  {
    "id": 128370,
    "slug": "akademia-tenisowa-tenis-kozerki",
    "name": "Akademia Tenisowa Tenis Kozerki",
    "link": "https://padellands.com/pistas-de-padel/akademia-tenisowa-tenis-kozerki/",
    "avatarUrl": "https://padellands.com/wp-content/uploads/2023/09/36ab4b761b7eeac815d4738fdd7c967a.jpeg",
    "courtsNumber": null,
    "cityFromDesc": null,
    "description": "",
    "sourceUrl": "https://padellands.com/pistas-de-padel/akademia-tenisowa-tenis-kozerki/",
    "cityRaw": "Kozerki",
    "address": "Kozerki",
    "phone": null,
    "website": null,
    "latitude": null,
    "longitude": null,
    "regionSlug": "polonia",
    "regionName": "Poland"
  },
  {
    "id": 128371,
    "slug": "carthago-wola",
    "name": "Carthago Wola",
    "link": "https://padellands.com/pistas-de-padel/carthago-wola/",
    "avatarUrl": "https://padellands.com/wp-content/uploads/2023/09/36ebe5ac6566cb75a4b5affe92209b93.jpeg",
    "courtsNumber": null,
    "cityFromDesc": null,
    "description": "",
    "sourceUrl": "https://padellands.com/pistas-de-padel/carthago-wola/",
    "cityRaw": "Turbia",
    "address": "Turbia",
    "phone": null,
    "website": null,
    "latitude": null,
    "longitude": null,
    "regionSlug": "polonia",
    "regionName": "Poland"
  },
  {
    "id": 128372,
    "slug": "via-sport-racket-center",
    "name": "Via Sport Racket Center",
    "link": "https://padellands.com/pistas-de-padel/via-sport-racket-center/",
    "avatarUrl": "https://padellands.com/wp-content/uploads/2023/09/859a10c5a871f878b3595ed1c3f2d9a6.jpeg",
    "courtsNumber": null,
    "cityFromDesc": null,
    "description": "",
    "sourceUrl": "https://padellands.com/pistas-de-padel/via-sport-racket-center/",
    "cityRaw": "Jaworzno",
    "address": "Jaworzno",
    "phone": null,
    "website": null,
    "latitude": null,
    "longitude": null,
    "regionSlug": "polonia",
    "regionName": "Poland"
  },
  {
    "id": 128373,
    "slug": "padel-carthagowola",
    "name": "Padel Carthagowola",
    "link": "https://padellands.com/pistas-de-padel/padel-carthagowola/",
    "avatarUrl": "https://padellands.com/wp-content/uploads/2023/09/a7590882728b2f4ec55d86f0de276592.jpeg",
    "courtsNumber": null,
    "cityFromDesc": null,
    "description": "",
    "sourceUrl": "https://padellands.com/pistas-de-padel/padel-carthagowola/",
    "cityRaw": "Zaleszany",
    "address": "Zaleszany",
    "phone": null,
    "website": null,
    "latitude": null,
    "longitude": null,
    "regionSlug": "polonia",
    "regionName": "Poland"
  },
  {
    "id": 128374,
    "slug": "fiesta-padel-wroclaw",
    "name": "Fiesta Padel Wrocław",
    "link": "https://padellands.com/pistas-de-padel/fiesta-padel-wroclaw/",
    "avatarUrl": "https://padellands.com/wp-content/uploads/2023/09/4f346397b88c078e9090b63f27cc0c58.png",
    "courtsNumber": null,
    "cityFromDesc": null,
    "description": "",
    "sourceUrl": "https://padellands.com/pistas-de-padel/fiesta-padel-wroclaw/",
    "cityRaw": "Wrocław",
    "address": "Wrocław",
    "phone": null,
    "website": null,
    "latitude": null,
    "longitude": null,
    "regionSlug": "polonia",
    "regionName": "Poland"
  },
  {
    "id": 128375,
    "slug": "k69",
    "name": "K69",
    "link": "https://padellands.com/pistas-de-padel/k69/",
    "avatarUrl": "https://padellands.com/wp-content/uploads/2023/09/ce6ff65037edf58d9fbd5b2655b8c103.png",
    "courtsNumber": null,
    "cityFromDesc": null,
    "description": "",
    "sourceUrl": "https://padellands.com/pistas-de-padel/k69/",
    "cityRaw": "Wrocław",
    "address": "Wrocław",
    "phone": null,
    "website": null,
    "latitude": null,
    "longitude": null,
    "regionSlug": "polonia",
    "regionName": "Poland"
  },
  {
    "id": 128360,
    "slug": "decathlon-targowek-warszawa",
    "name": "Decathlon Targówek Warszawa",
    "link": "https://padellands.com/pistas-de-padel/decathlon-targowek-warszawa/",
    "avatarUrl": "https://padellands.com/wp-content/uploads/2024/04/Decathlon.jpeg",
    "courtsNumber": null,
    "cityFromDesc": null,
    "description": "",
    "sourceUrl": "https://padellands.com/pistas-de-padel/decathlon-targowek-warszawa/",
    "cityRaw": "Varsovia",
    "address": "Varsovia",
    "phone": null,
    "website": null,
    "latitude": null,
    "longitude": null,
    "regionSlug": "polonia",
    "regionName": "Poland"
  },
  {
    "id": 128376,
    "slug": "padel-pl-wroclaw",
    "name": "Padel PL Wrocław",
    "link": "https://padellands.com/pistas-de-padel/padel-pl-wroclaw/",
    "avatarUrl": "https://padellands.com/wp-content/uploads/2023/09/4655f9fd658af80578c530587d5a655b.jpeg",
    "courtsNumber": null,
    "cityFromDesc": null,
    "description": "",
    "sourceUrl": "https://padellands.com/pistas-de-padel/padel-pl-wroclaw/",
    "cityRaw": "Wrocław",
    "address": "Wrocław",
    "phone": null,
    "website": null,
    "latitude": null,
    "longitude": null,
    "regionSlug": "polonia",
    "regionName": "Poland"
  },
  {
    "id": 128361,
    "slug": "padel-tenis-plaza-wilanow",
    "name": "Padel & Tenis Plaża Wilanów",
    "link": "https://padellands.com/pistas-de-padel/padel-tenis-plaza-wilanow/",
    "avatarUrl": null,
    "courtsNumber": null,
    "cityFromDesc": null,
    "description": "",
    "sourceUrl": "https://padellands.com/pistas-de-padel/padel-tenis-plaza-wilanow/",
    "cityRaw": "Varsovia",
    "address": "Varsovia",
    "phone": null,
    "website": null,
    "latitude": null,
    "longitude": null,
    "regionSlug": "polonia",
    "regionName": "Poland"
  },
  {
    "id": 128377,
    "slug": "interpadel-torun",
    "name": "Interpadel Torun",
    "link": "https://padellands.com/pistas-de-padel/interpadel-torun/",
    "avatarUrl": "https://padellands.com/wp-content/uploads/2023/09/b2f5f6fc04626b0c157a8c51608a762f.png",
    "courtsNumber": null,
    "cityFromDesc": null,
    "description": "",
    "sourceUrl": "https://padellands.com/pistas-de-padel/interpadel-torun/",
    "cityRaw": "Toruń",
    "address": "Toruń",
    "phone": null,
    "website": null,
    "latitude": null,
    "longitude": null,
    "regionSlug": "polonia",
    "regionName": "Poland"
  },
  {
    "id": 128362,
    "slug": "moris-chorzow",
    "name": "MORiS Chorzów",
    "link": "https://padellands.com/pistas-de-padel/moris-chorzow/",
    "avatarUrl": "https://padellands.com/wp-content/uploads/2023/09/0ff14d8d33f51b82937d9715a024eee8.jpg",
    "courtsNumber": null,
    "cityFromDesc": null,
    "description": "",
    "sourceUrl": "https://padellands.com/pistas-de-padel/moris-chorzow/",
    "cityRaw": "Chorzow",
    "address": "Chorzow",
    "phone": null,
    "website": null,
    "latitude": null,
    "longitude": null,
    "regionSlug": "polonia",
    "regionName": "Poland"
  },
  {
    "id": 128378,
    "slug": "interpadel-warszawa",
    "name": "Interpadel Warszawa",
    "link": "https://padellands.com/pistas-de-padel/interpadel-warszawa/",
    "avatarUrl": "https://padellands.com/wp-content/uploads/2023/09/b2f5f6fc04626b0c157a8c51608a762f.png",
    "courtsNumber": null,
    "cityFromDesc": null,
    "description": "",
    "sourceUrl": "https://padellands.com/pistas-de-padel/interpadel-warszawa/",
    "cityRaw": "Warszawa",
    "address": "Warszawa",
    "phone": null,
    "website": null,
    "latitude": null,
    "longitude": null,
    "regionSlug": "polonia",
    "regionName": "Poland"
  },
  {
    "id": 128363,
    "slug": "dom-kultury-w-wolbromiu",
    "name": "Dom Kultury w Wolbromiu",
    "link": "https://padellands.com/pistas-de-padel/dom-kultury-w-wolbromiu/",
    "avatarUrl": "https://padellands.com/wp-content/uploads/2023/09/5581791be4117c759f53c8fef785d959.png",
    "courtsNumber": null,
    "cityFromDesc": null,
    "description": "",
    "sourceUrl": "https://padellands.com/pistas-de-padel/dom-kultury-w-wolbromiu/",
    "cityRaw": "Wolbrom",
    "address": "Wolbrom",
    "phone": null,
    "website": null,
    "latitude": null,
    "longitude": null,
    "regionSlug": "polonia",
    "regionName": "Poland"
  },
  {
    "id": 128379,
    "slug": "sierra-golf-resort",
    "name": "Sierra Golf Resort",
    "link": "https://padellands.com/pistas-de-padel/sierra-golf-resort/",
    "avatarUrl": "https://padellands.com/wp-content/uploads/2023/09/23de952c87ceee3c581b6bcb7c82757a.jpeg",
    "courtsNumber": null,
    "cityFromDesc": null,
    "description": "",
    "sourceUrl": "https://padellands.com/pistas-de-padel/sierra-golf-resort/",
    "cityRaw": "Wejherowo",
    "address": "Wejherowo",
    "phone": null,
    "website": null,
    "latitude": null,
    "longitude": null,
    "regionSlug": "polonia",
    "regionName": "Poland"
  },
  {
    "id": 128364,
    "slug": "pomorska-tenis-park",
    "name": "Pomorska Tenis Park",
    "link": "https://padellands.com/pistas-de-padel/pomorska-tenis-park/",
    "avatarUrl": "https://padellands.com/wp-content/uploads/2023/09/734369f7c0be5233e35a6c2791db5ad9.jpg",
    "courtsNumber": null,
    "cityFromDesc": null,
    "description": "",
    "sourceUrl": "https://padellands.com/pistas-de-padel/pomorska-tenis-park/",
    "cityRaw": "Łódź",
    "address": "Łódź",
    "phone": null,
    "website": null,
    "latitude": null,
    "longitude": null,
    "regionSlug": "polonia",
    "regionName": "Poland"
  },
  {
    "id": 128365,
    "slug": "fame-sport-club",
    "name": "Fame Sport Club",
    "link": "https://padellands.com/pistas-de-padel/fame-sport-club/",
    "avatarUrl": "https://padellands.com/wp-content/uploads/2023/09/e1d98669db5a605aeb483e32d4301d50.jpeg",
    "courtsNumber": null,
    "cityFromDesc": null,
    "description": "",
    "sourceUrl": "https://padellands.com/pistas-de-padel/fame-sport-club/",
    "cityRaw": "Cracovia",
    "address": "Cracovia",
    "phone": null,
    "website": null,
    "latitude": null,
    "longitude": null,
    "regionSlug": "polonia",
    "regionName": "Poland"
  },
  {
    "id": 128366,
    "slug": "happy-padel-wesola",
    "name": "HAPPY PADEL Wesoła",
    "link": "https://padellands.com/pistas-de-padel/happy-padel-wesola/",
    "avatarUrl": "https://padellands.com/wp-content/uploads/2023/09/94c8247dba15c3bd380688c04cd14cec.jpeg",
    "courtsNumber": null,
    "cityFromDesc": null,
    "description": "",
    "sourceUrl": "https://padellands.com/pistas-de-padel/happy-padel-wesola/",
    "cityRaw": "Varsovia",
    "address": "Varsovia",
    "phone": null,
    "website": null,
    "latitude": null,
    "longitude": null,
    "regionSlug": "polonia",
    "regionName": "Poland"
  },
  {
    "id": 128367,
    "slug": "padel-dabrowa-gornicza",
    "name": "Padel Dąbrowa Górnicza",
    "link": "https://padellands.com/pistas-de-padel/padel-dabrowa-gornicza/",
    "avatarUrl": null,
    "courtsNumber": null,
    "cityFromDesc": null,
    "description": "",
    "sourceUrl": "https://padellands.com/pistas-de-padel/padel-dabrowa-gornicza/",
    "cityRaw": "Dabrowa Gornicza",
    "address": "Dabrowa Gornicza",
    "phone": null,
    "website": null,
    "latitude": null,
    "longitude": null,
    "regionSlug": "polonia",
    "regionName": "Poland"
  },
  {
    "id": 128368,
    "slug": "korty-morskie-oko",
    "name": "Korty Morskie Oko",
    "link": "https://padellands.com/pistas-de-padel/korty-morskie-oko/",
    "avatarUrl": "https://padellands.com/wp-content/uploads/2023/09/b89867f5d12318dfdb2de68d45e31278.jpg",
    "courtsNumber": null,
    "cityFromDesc": null,
    "description": "",
    "sourceUrl": "https://padellands.com/pistas-de-padel/korty-morskie-oko/",
    "cityRaw": "Wrocław",
    "address": "Wrocław",
    "phone": null,
    "website": null,
    "latitude": null,
    "longitude": null,
    "regionSlug": "polonia",
    "regionName": "Poland"
  },
  {
    "id": 128355,
    "slug": "point-sport-club",
    "name": "POINT SPORT CLUB",
    "link": "https://padellands.com/pistas-de-padel/point-sport-club/",
    "avatarUrl": "https://padellands.com/wp-content/uploads/2023/09/15506d2461bd38a47b5eba3a5b6baaea.jpg",
    "courtsNumber": null,
    "cityFromDesc": null,
    "description": "",
    "sourceUrl": "https://padellands.com/pistas-de-padel/point-sport-club/",
    "cityRaw": "Bilcza",
    "address": "Bilcza",
    "phone": null,
    "website": null,
    "latitude": null,
    "longitude": null,
    "regionSlug": "polonia",
    "regionName": "Poland"
  },
  {
    "id": 128356,
    "slug": "padel-sopot",
    "name": "PADEL SOPOT",
    "link": "https://padellands.com/pistas-de-padel/padel-sopot/",
    "avatarUrl": "https://padellands.com/wp-content/uploads/2023/09/882c6488388914c9db6902d763d52741.jpg",
    "courtsNumber": null,
    "cityFromDesc": null,
    "description": "",
    "sourceUrl": "https://padellands.com/pistas-de-padel/padel-sopot/",
    "cityRaw": "Sopot",
    "address": "Sopot",
    "phone": null,
    "website": null,
    "latitude": null,
    "longitude": null,
    "regionSlug": "polonia",
    "regionName": "Poland"
  },
  {
    "id": 128357,
    "slug": "propadel-jutrzenki",
    "name": "ProPadel Jutrzenki",
    "link": "https://padellands.com/pistas-de-padel/propadel-jutrzenki/",
    "avatarUrl": "https://padellands.com/wp-content/uploads/2024/01/ProPadel-Jutrzenki.jpeg",
    "courtsNumber": null,
    "cityFromDesc": null,
    "description": "ProPadel Jutrzenki",
    "sourceUrl": "https://padellands.com/pistas-de-padel/propadel-jutrzenki/",
    "cityRaw": "Varsovia",
    "address": "Varsovia",
    "phone": null,
    "website": null,
    "latitude": null,
    "longitude": null,
    "regionSlug": "polonia",
    "regionName": "Poland"
  },
  {
    "id": 128358,
    "slug": "sinus-sport-club",
    "name": "SINUS SPORT CLUB",
    "link": "https://padellands.com/pistas-de-padel/sinus-sport-club/",
    "avatarUrl": "https://padellands.com/wp-content/uploads/2023/09/28721237a3bd6d79c5330419f0fede70.jpg",
    "courtsNumber": null,
    "cityFromDesc": null,
    "description": "",
    "sourceUrl": "https://padellands.com/pistas-de-padel/sinus-sport-club/",
    "cityRaw": "Varsovia",
    "address": "Varsovia",
    "phone": null,
    "website": null,
    "latitude": null,
    "longitude": null,
    "regionSlug": "polonia",
    "regionName": "Poland"
  },
  {
    "id": 128359,
    "slug": "wkt-mera",
    "name": "WKT MERA",
    "link": "https://padellands.com/pistas-de-padel/wkt-mera/",
    "avatarUrl": "https://padellands.com/wp-content/uploads/2023/09/58cb4cfa39dbe48f4353dd7c189d7c86.jpg",
    "courtsNumber": null,
    "cityFromDesc": null,
    "description": "",
    "sourceUrl": "https://padellands.com/pistas-de-padel/wkt-mera/",
    "cityRaw": "Varsovia",
    "address": "Varsovia",
    "phone": null,
    "website": null,
    "latitude": null,
    "longitude": null,
    "regionSlug": "polonia",
    "regionName": "Poland"
  }
]